{
 "id": "3",
 "error": 0.17081849472306024,
 "resolution": {
  "height": 540,
  "width": 960
 },
 "intrinsic": {
  "shape": {
   "dims": [
    {
     "size": 3,
     "name": "rows"
    },
    {
     "size": 3,
     "name": "cols"
    }
   ]
  },
  "type": "DOUBLE_TYPE",
  "floats": [],
  "doubles": [
   908.64696111390845,
   0,
   481.06794312463308,
   0,
   1262.6096327849577,
   274.99603839155236,
   0,
   0,
   1
  ],
  "ints32": [],
  "ints64": []
 },
 "distortion": {
  "shape": {
   "dims": [
    {
     "size": 1,
     "name": "rows"
    },
    {
     "size": 5,
     "name": "cols"
    }
   ]
  },
  "type": "DOUBLE_TYPE",
  "floats": [],
  "doubles": [
   -0.82630324388535359,
   10.775767898277982,
   -0.0099839322027270756,
   -0.00070851249745133762,
   -55.626639808845532
  ],
  "ints32": [],
  "ints64": []
 },
 "extrinsic": [],
 "calibratedAt": "2021-11-27T15:44:02.561290557Z"
}
